<?xml version="1.0" encoding="UTF-8"?>
<R2H_Task_UserParameters>
  <HostCPU>
    <Address>0x3E00</Address>
  </HostCPU>
  <ExtensionModules>
    <ExtensionModule>
      <ID>0x1001</ID>
      <Name>R12CCPU_V_SMART_ECAT</Name>
      <Switch>0x00000000</Switch>
      <Address>0x3E10</Address>
      <BitSize>0x0010</BitSize>
      <ExtraInputDataOffset>0</ExtraInputDataOffset>
      <ExtraInputDataSize>256</ExtraInputDataSize>
      <ExtraOutputDataOffset>0</ExtraOutputDataOffset>
      <ExtraOutputDataSize>256</ExtraOutputDataSize>
      <ENI>/2/lpcvd2.xml</ENI>
    </ExtensionModule>
    <ExtensionModule>
      <ID>0x0004</ID>
      <Name>RX42C4</Name>
      <Switch>0x00000000</Switch>
      <Address>0x0020</Address>
      <BitSize>0x0040</BitSize>
    </ExtensionModule>
    <ExtensionModule>
      <ID>0x0004</ID>
      <Name>RX42C4</Name>
      <Switch>0x00000000</Switch>
      <Address>0x0060</Address>
      <BitSize>0x0040</BitSize>
    </ExtensionModule>
    <ExtensionModule>
      <ID>0x000D</ID>
      <Name>RY42NT2P</Name>
      <Switch>0x00000000</Switch>
      <Address>0x00A0</Address>
      <BitSize>0x0040</BitSize>
    </ExtensionModule>
    <ExtensionModule>
      <ID>0x0012</ID>
      <Name>RH42C4NT2P</Name>
      <Switch>0x00000000</Switch>
      <Address>0x00E0</Address>
      <BitSize>0x0020</BitSize>
    </ExtensionModule>
    <ExtensionModule>
      <ID>0x0021</ID>
      <Name>R60ADV8</Name>
      <Switch>0x44444444</Switch>
      <Address>0x0100</Address>
      <BitSize>0x0010</BitSize>
    </ExtensionModule>
    <ExtensionModule>
      <ID>0x0031</ID>
      <Name>R60DAV8</Name>
      <Switch>0x44444444</Switch>
      <Address>0x0110</Address>
      <BitSize>0x0010</BitSize>
    </ExtensionModule>
    <ExtensionModule>
      <ID>0x0041</ID>
      <Name>R60RD8_G</Name>
      <Switch>0x11111111</Switch>
      <Address>0x0120</Address>
      <BitSize>0x0010</BitSize>
    </ExtensionModule>
    <ExtensionModule>
      <ID>0x000D</ID>
      <Name>RY42NT2P</Name>
      <Switch>0x00000000</Switch>
      <Address>0x0150</Address>
      <BitSize>0x0040</BitSize>
    </ExtensionModule>
    <ExtensionModule>
      <ID>0x0021</ID>
      <Name>R60ADV8</Name>
      <Switch>0x44444444</Switch>
      <Address>0x0190</Address>
      <BitSize>0x0010</BitSize>
    </ExtensionModule>
    <ExtensionModule>
      <ID>0x0021</ID>
      <Name>R60ADV8</Name>
      <Switch>0x44444444</Switch>
      <Address>0x01A0</Address>
      <BitSize>0x0010</BitSize>
    </ExtensionModule>
    <ExtensionModule>
      <ID>0x0041</ID>
      <Name>R60RD8_G</Name>
      <Switch>0x11111111</Switch>
      <Address>0x01B0</Address>
      <BitSize>0x0010</BitSize>
    </ExtensionModule>
    <ExtensionModule>
      <ID>0x8005</ID>
      <Name>GENERAL_SOFT_CCPU_W</Name>
      <Switch>0x00000000</Switch>
      <Address>0x1000</Address>
      <BitSize>0x0010</BitSize>
      <ExtraInputDataOffset>0</ExtraInputDataOffset>
      <ExtraInputDataSize>128</ExtraInputDataSize>
      <ExtraOutputDataOffset>296</ExtraOutputDataOffset>
      <ExtraOutputDataSize>128</ExtraOutputDataSize>
    </ExtensionModule>
  </ExtensionModules>
  <EthernetModules />
</R2H_Task_UserParameters>